Config.py
__init__.py
auth.py
command.py
config_template.py
exceptions.py
utils.py
Reger/__init__.py
Reger/config.py
Reger/models.py
Reger/options.py
Reger/roles_options.py
Reger/service.py
Service/communicator.py
Service/config.py
Service/models.py
Service/permission.py
Service/service.py
Service/test.py
ServeLite-0.0.5.dist-info/METADATA
ServeLite-0.0.5.dist-info/WHEEL
ServeLite-0.0.5.dist-info/entry_points.txt
ServeLite-0.0.5.dist-info/top_level.txt
ServeLite-0.0.5.dist-info/RECORD
