Metadata-Version: 2.1
Name: ServeLite
Version: 0.0.5
Summary: 基于flask的轻量级服务化框架
Home-page: https://github.com/AlllenShen/ServeLite
Author: Allen Shen
Author-email: 932142511@qq.com
License: UNKNOWN
Platform: UNKNOWN
